schemahq/__init__.py
schemahq/cli.py
schemahq/roles.py
schemahq/schemahq.py
schemahq-0.1.15.dist-info/entry_points.txt
schemahq-0.1.15.dist-info/WHEEL
schemahq-0.1.15.dist-info/METADATA
schemahq-0.1.15.dist-info/RECORD
